Metadata-Version: 1.0
Name: pmcy-distributions
Version: 0.1
Summary: Gaussian distributions
Home-page: UNKNOWN
Author: Petros Mina
Author-email: petros.mina@gmail.com
License: UNKNOWN
Platform: UNKNOWN
